cr_learn/__init__.py
cr_learn/beibei.py
cr_learn/cli.py
cr_learn/ijcai.py
cr_learn/library_thing.py
cr_learn/ml_1m.py
cr_learn/rees46.py
cr_learn/steam_games.py
cr_learn/tmall.py
cr_learn/CRDS/CRDS_Dashboard.py
cr_learn/CRDS/CRDS_Health.py
cr_learn/CRDS/__init__.py
cr_learn/utils/__init__.py
cr_learn/utils/cr_cache_path.py
cr_learn/utils/gdrive_downloader.py
cr_learn/utils/vish_exception.py
cr_learn-0.1.7.dist-info/LICENSE.txt
cr_learn-0.1.7.dist-info/METADATA
cr_learn-0.1.7.dist-info/WHEEL
cr_learn-0.1.7.dist-info/entry_points.txt
cr_learn-0.1.7.dist-info/top_level.txt
cr_learn-0.1.7.dist-info/RECORD
