Metadata-Version: 2.1
Name: cr_learn
Version: 0.1.7
Summary: A Library Provides Bunch of datasets to speed up your recsys learing.
Author: vishesh yadav
Author-email: vishesh@corerec.tech
Requires-Python: >=3.7
License-File: LICENSE.txt
Requires-Dist: pandas
Requires-Dist: numpy
Requires-Dist: torch
Requires-Dist: gdown
Requires-Dist: tqdm
Requires-Dist: requests
